README.md
setup.py
universal_object_pool/__init__.py
universal_object_pool.egg-info/PKG-INFO
universal_object_pool.egg-info/SOURCES.txt
universal_object_pool.egg-info/dependency_links.txt
universal_object_pool.egg-info/requires.txt
universal_object_pool.egg-info/top_level.txt
universal_object_pool/contrib/__init__.py
universal_object_pool/contrib/http_pool.py
universal_object_pool/contrib/mock_spend_time_object_use_object_pool.py
universal_object_pool/contrib/paramiko_pool.py
universal_object_pool/contrib/pika_pool.py
universal_object_pool/contrib/pymysql_pool.py
universal_object_pool/contrib/threadpool_using_object_pool.py
universal_object_pool/contrib/webdriver_pool.py